arcane/core/__init__.py
arcane/core/compute_names.py
arcane/core/const.py
arcane/core/datastore_kind.py
arcane/core/exceptions.py
arcane/core/types.py
arcane/core/utils.py
arcane_core-1.33.9.dist-info/METADATA
arcane_core-1.33.9.dist-info/WHEEL
arcane_core-1.33.9.dist-info/RECORD
