Metadata-Version: 2.4
Name: arcane-core
Version: 1.33.9
Summary: Common utility functions
Author: Arcane
Author-email: product@wearcane.com
Requires-Python: >=3.7,<4.0
Classifier: Programming Language :: Python :: 3
Classifier: Programming Language :: Python :: 3.7
Classifier: Programming Language :: Python :: 3.8
Classifier: Programming Language :: Python :: 3.9
Classifier: Programming Language :: Python :: 3.10
Classifier: Programming Language :: Python :: 3.11
Classifier: Programming Language :: Python :: 3.12
Classifier: Programming Language :: Python :: 3.13
Classifier: Programming Language :: Python :: 3.14
Requires-Dist: google-cloud-core (>=2.3,<3.0)
Requires-Dist: typing-extensions (>=3.7)
